syspro_connect/__init__.py
syspro_connect/bomfinder.py
syspro_connect/syspro.py
syspro_connect/utils.py
syspro_connect-0.1.2.dist-info/WHEEL
syspro_connect-0.1.2.dist-info/METADATA
syspro_connect-0.1.2.dist-info/RECORD
