Metadata-Version: 2.1
Name: syspro-connect
Version: 0.1.2
Summary: 
Author: w-ejt
Author-email: 97180065+w-ejt@users.noreply.github.com
Requires-Python: >=3.10,<4.0
Classifier: Programming Language :: Python :: 3
Classifier: Programming Language :: Python :: 3.10
Classifier: Programming Language :: Python :: 3.11
Requires-Dist: pandas (>=1.5.3,<2.0.0)
Requires-Dist: pyodbc (>=4.0.35,<5.0.0)
Requires-Dist: python-dotenv (>=0.21.0,<0.22.0)
Requires-Dist: sqlalchemy (>=1.4.46,<2.0.0)
